README.md
setup.py
client/__init__.py
client/client.py
conf/__init__.py
conf/config.py
lib/__init__.py
lib/func_ext.py
lib/http_post.py
lib/log.py
lib/pyamqp.py
shopex_dingding_notify_2.x.x.egg-info/PKG-INFO
shopex_dingding_notify_2.x.x.egg-info/SOURCES.txt
shopex_dingding_notify_2.x.x.egg-info/dependency_links.txt
shopex_dingding_notify_2.x.x.egg-info/top_level.txt
test/SendMessageToDingDingTestCase.py
test/SendMessageToMqTestCase.py
test/__init__.py