Metadata-Version: 2.1
Name: shopex-dingding-notify-2.x.x
Version: 1.0
Summary: ShopEx dingding notify for python
Home-page: https://github.com/magic119/shopex-dingding-notify-2.x.git
Author: ShopEx
Author-email: xuhongtao@shopex.cn
License: LGPL
Platform: README.md
Requires-Python: >=2.7.0, <2.7.18
